{
  "generatedAt": "2026-06-19T03:26:58.701Z",
  "chains": [
    {
      "network": "OP Mainnet",
      "chainId": 10,
      "tvlUsd": 300893769.712615,
      "dexVolume24hUsd": 24261925,
      "dexVolume7dUsd": 135294060,
      "dexVolume30dUsd": 660365726,
      "fees24hUsd": 149620,
      "fees7dUsd": 1002769,
      "fees30dUsd": 4515246,
      "sourceUrl": "https://defillama.com/chains"
    },
    {
      "network": "Base",
      "chainId": 8453,
      "tvlUsd": 4154617881.123043,
      "dexVolume24hUsd": 1043429048,
      "dexVolume7dUsd": 6285945836,
      "dexVolume30dUsd": 35144837489,
      "fees24hUsd": 1946417,
      "fees7dUsd": 12265778,
      "fees30dUsd": 79684432,
      "sourceUrl": "https://defillama.com/chains"
    },
    {
      "network": "Unichain",
      "chainId": 130,
      "tvlUsd": 23320803.52187518,
      "dexVolume24hUsd": 17207742,
      "dexVolume7dUsd": 89369913,
      "dexVolume30dUsd": 306544459,
      "fees24hUsd": 30002,
      "fees7dUsd": 160757,
      "fees30dUsd": 493644,
      "sourceUrl": "https://defillama.com/chains"
    },
    {
      "network": "Mode",
      "chainId": 34443,
      "tvlUsd": 1852968.894740747,
      "dexVolume24hUsd": 5665,
      "dexVolume7dUsd": 57617,
      "dexVolume30dUsd": 298296,
      "fees24hUsd": 11,
      "fees7dUsd": 63,
      "fees30dUsd": 257,
      "sourceUrl": "https://defillama.com/chains"
    },
    {
      "network": "Zora",
      "chainId": 7777777,
      "tvlUsd": 33130.015031214294,
      "dexVolume24hUsd": 64,
      "dexVolume7dUsd": 396,
      "dexVolume30dUsd": 1739,
      "fees24hUsd": 0,
      "fees7dUsd": 0,
      "fees30dUsd": 22,
      "sourceUrl": "https://defillama.com/chains"
    }
  ],
  "topMarkets": [
    {
      "id": "10-velodrome-v3",
      "network": "OP Mainnet",
      "dex": "Velodrome V3",
      "slug": "velodrome-v3",
      "category": "Dexs",
      "priority": true,
      "volume24hUsd": 12034812,
      "volume7dUsd": 65109158,
      "volume30dUsd": 304481068,
      "fees24hUsd": 4981,
      "fees7dUsd": 30130,
      "fees30dUsd": 130173,
      "change1dPct": 4.62,
      "change7dPct": 18.98,
      "change30dPct": 69.28,
      "feeToVolume30dPct": 0.042752411785418463,
      "health": "Strong",
      "outcomeTarget": "Rebalance liquidity",
      "sourceUrl": "https://defillama.com/protocol/velodrome-v3",
      "updatedAt": "2026-06-19T03:26:58.701Z"
    },
    {
      "id": "10-uniswap-v3",
      "network": "OP Mainnet",
      "dex": "Uniswap V3",
      "slug": "uniswap-v3",
      "category": "Dexs",
      "priority": true,
      "volume24hUsd": 4904464,
      "volume7dUsd": 32927026,
      "volume30dUsd": 210833670,
      "fees24hUsd": 10673,
      "fees7dUsd": 74112,
      "fees30dUsd": 468978,
      "change1dPct": -31.89,
      "change7dPct": -5.13,
      "change30dPct": 23.87,
      "feeToVolume30dPct": 0.22243980290244914,
      "health": "Strong",
      "outcomeTarget": "Rebalance liquidity",
      "sourceUrl": "https://defillama.com/protocol/uniswap-v3",
      "updatedAt": "2026-06-19T03:26:58.701Z"
    },
    {
      "id": "10-uniswap-v4",
      "network": "OP Mainnet",
      "dex": "Uniswap V4",
      "slug": "uniswap-v4",
      "category": "Dexs",
      "priority": true,
      "volume24hUsd": 1250026,
      "volume7dUsd": 6281741,
      "volume30dUsd": 24811213,
      "fees24hUsd": 1585,
      "fees7dUsd": 7617,
      "fees30dUsd": 15652,
      "change1dPct": 71.79,
      "change7dPct": 22.08,
      "change30dPct": 248.87,
      "feeToVolume30dPct": 0.06308438043718378,
      "health": "Strong",
      "outcomeTarget": "Rebalance liquidity",
      "sourceUrl": "https://defillama.com/protocol/uniswap-v4",
      "updatedAt": "2026-06-19T03:26:58.701Z"
    },
    {
      "id": "10-velodrome-v2",
      "network": "OP Mainnet",
      "dex": "Velodrome V2",
      "slug": "velodrome-v2",
      "category": "Dexs",
      "priority": true,
      "volume24hUsd": 315472,
      "volume7dUsd": 2543684,
      "volume30dUsd": 11869509,
      "fees24hUsd": 829,
      "fees7dUsd": 16545,
      "fees30dUsd": 26031,
      "change1dPct": -24.46,
      "change7dPct": -36.23,
      "change30dPct": 84.24,
      "feeToVolume30dPct": 0.21930982991798567,
      "health": "Watch",
      "outcomeTarget": "Monitor incentives",
      "sourceUrl": "https://defillama.com/protocol/velodrome-v2",
      "updatedAt": "2026-06-19T03:26:58.701Z"
    },
    {
      "id": "10-solidly-v3",
      "network": "OP Mainnet",
      "dex": "Solidly V3",
      "slug": "solidly-v3",
      "category": "Dexs",
      "priority": true,
      "volume24hUsd": 97397,
      "volume7dUsd": 953703,
      "volume30dUsd": 6880918,
      "fees24hUsd": null,
      "fees7dUsd": null,
      "fees30dUsd": null,
      "change1dPct": -53.82,
      "change7dPct": -21.32,
      "change30dPct": -10.67,
      "feeToVolume30dPct": null,
      "health": "Watch",
      "outcomeTarget": "Monitor incentives",
      "sourceUrl": "https://defillama.com/protocol/solidly-v3",
      "updatedAt": "2026-06-19T03:26:58.701Z"
    },
    {
      "id": "10-woofi-swap",
      "network": "OP Mainnet",
      "dex": "WOOFi Swap",
      "slug": "woofi-swap",
      "category": "Dexs",
      "priority": true,
      "volume24hUsd": 1888869,
      "volume7dUsd": 5013261,
      "volume30dUsd": 5013261,
      "fees24hUsd": 491,
      "fees7dUsd": 498,
      "fees30dUsd": 498,
      "change1dPct": 241.05,
      "change7dPct": null,
      "change30dPct": null,
      "feeToVolume30dPct": 0.009933653962959439,
      "health": "Strong",
      "outcomeTarget": "Improve fee efficiency",
      "sourceUrl": "https://defillama.com/protocol/woofi-swap",
      "updatedAt": "2026-06-19T03:26:58.701Z"
    },
    {
      "id": "10-curve-dex",
      "network": "OP Mainnet",
      "dex": "Curve DEX",
      "slug": "curve-dex",
      "category": "Dexs",
      "priority": true,
      "volume24hUsd": 120523,
      "volume7dUsd": 603412,
      "volume30dUsd": 4199127,
      "fees24hUsd": 38,
      "fees7dUsd": 243,
      "fees30dUsd": 1281,
      "change1dPct": 96.34,
      "change7dPct": -21.85,
      "change30dPct": 109.51,
      "feeToVolume30dPct": 0.030506340960871153,
      "health": "Watch",
      "outcomeTarget": "Monitor incentives",
      "sourceUrl": "https://defillama.com/protocol/curve-dex",
      "updatedAt": "2026-06-19T03:26:58.701Z"
    },
    {
      "id": "10-sushiswap-v3",
      "network": "OP Mainnet",
      "dex": "SushiSwap V3",
      "slug": "sushiswap-v3",
      "category": "Dexs",
      "priority": true,
      "volume24hUsd": 17863,
      "volume7dUsd": 91163,
      "volume30dUsd": 1084345,
      "fees24hUsd": 9,
      "fees7dUsd": 56,
      "fees30dUsd": 468,
      "change1dPct": -12.47,
      "change7dPct": 14.05,
      "change30dPct": 26.71,
      "feeToVolume30dPct": 0.04315969548437075,
      "health": "Watch",
      "outcomeTarget": "Rebalance liquidity",
      "sourceUrl": "https://defillama.com/protocol/sushiswap-v3",
      "updatedAt": "2026-06-19T03:26:58.701Z"
    },
    {
      "id": "10-beets-dex",
      "network": "OP Mainnet",
      "dex": "Beets DEX",
      "slug": "beets-dex",
      "category": "Dexs",
      "priority": true,
      "volume24hUsd": 118812,
      "volume7dUsd": 171617,
      "volume30dUsd": 793639,
      "fees24hUsd": 7,
      "fees7dUsd": 24,
      "fees30dUsd": 266,
      "change1dPct": 1486.28,
      "change7dPct": 768,
      "change30dPct": 989.92,
      "feeToVolume30dPct": 0.0335164980551611,
      "health": "Watch",
      "outcomeTarget": "Rebalance liquidity",
      "sourceUrl": "https://defillama.com/protocol/beets-dex",
      "updatedAt": "2026-06-19T03:26:58.701Z"
    },
    {
      "id": "10-balancer-v2",
      "network": "OP Mainnet",
      "dex": "Balancer V2",
      "slug": "balancer-v2",
      "category": "Dexs",
      "priority": true,
      "volume24hUsd": 113280,
      "volume7dUsd": 167023,
      "volume30dUsd": 762077,
      "fees24hUsd": 7,
      "fees7dUsd": 24,
      "fees30dUsd": 261,
      "change1dPct": 1441.01,
      "change7dPct": 1400,
      "change30dPct": 940.89,
      "feeToVolume30dPct": 0.03424850769672881,
      "health": "Watch",
      "outcomeTarget": "Rebalance liquidity",
      "sourceUrl": "https://defillama.com/protocol/balancer-v2",
      "updatedAt": "2026-06-19T03:26:58.701Z"
    },
    {
      "id": "8453-aerodrome-slipstream",
      "network": "Base",
      "dex": "Aerodrome Slipstream",
      "slug": "aerodrome-slipstream",
      "category": "Dexs",
      "priority": true,
      "volume24hUsd": 433174959,
      "volume7dUsd": 2877141454,
      "volume30dUsd": 17451932840,
      "fees24hUsd": 222932,
      "fees7dUsd": 1391182,
      "fees30dUsd": 8348335,
      "change1dPct": -15.65,
      "change7dPct": -12.47,
      "change30dPct": -18.97,
      "feeToVolume30dPct": 0.04783616277083954,
      "health": "Watch",
      "outcomeTarget": "Rebalance liquidity",
      "sourceUrl": "https://defillama.com/protocol/aerodrome-slipstream",
      "updatedAt": "2026-06-19T03:26:58.701Z"
    },
    {
      "id": "8453-uniswap-v4",
      "network": "Base",
      "dex": "Uniswap V4",
      "slug": "uniswap-v4",
      "category": "Dexs",
      "priority": true,
      "volume24hUsd": 329182144,
      "volume7dUsd": 1605522685,
      "volume30dUsd": 7297681327,
      "fees24hUsd": 310950,
      "fees7dUsd": 1516379,
      "fees30dUsd": 12799587,
      "change1dPct": 20.35,
      "change7dPct": 68.54,
      "change30dPct": 44.73,
      "feeToVolume30dPct": 0.17539251751983223,
      "health": "Strong",
      "outcomeTarget": "Rebalance liquidity",
      "sourceUrl": "https://defillama.com/protocol/uniswap-v4",
      "updatedAt": "2026-06-19T03:26:58.701Z"
    }
  ],
  "topProtocols": [
    {
      "id": "uniswap",
      "name": "Uniswap",
      "segment": "Core Superchain liquidity venue",
      "networks": [
        "Base",
        "OP Mainnet",
        "Unichain",
        "Zora"
      ],
      "marketCount": 8,
      "volume30dUsd": 11183690583,
      "fees30dUsd": 24471675,
      "feeToVolume30dPct": 0.21881573724150302,
      "weightedChange7dPct": 41.405940878778516,
      "strongMarkets": 5,
      "watchMarkets": 1,
      "atRiskMarkets": 2,
      "score": 98,
      "confidence": 100,
      "status": "Ready for report",
      "sourceUrls": [
        "https://defillama.com/protocol/uniswap-v3",
        "https://defillama.com/protocol/uniswap-v4",
        "https://defillama.com/protocol/uniswap-v2"
      ],
      "updatedAt": "2026-06-19T03:26:58.701Z"
    },
    {
      "id": "velodrome",
      "name": "Velodrome",
      "segment": "OP-aligned liquidity hub",
      "networks": [
        "Mode",
        "OP Mainnet",
        "Unichain"
      ],
      "marketCount": 5,
      "volume30dUsd": 324125691,
      "fees30dUsd": 157572,
      "feeToVolume30dPct": 0.048614474068332955,
      "weightedChange7dPct": 16.256597218206938,
      "strongMarkets": 2,
      "watchMarkets": 1,
      "atRiskMarkets": 2,
      "score": 84,
      "confidence": 100,
      "status": "Ready for report",
      "sourceUrls": [
        "https://defillama.com/protocol/velodrome-v3",
        "https://defillama.com/protocol/velodrome-v2"
      ],
      "updatedAt": "2026-06-19T03:26:58.701Z"
    },
    {
      "id": "aerodrome",
      "name": "Aerodrome",
      "segment": "Base liquidity hub",
      "networks": [
        "Base"
      ],
      "marketCount": 2,
      "volume30dUsd": 17806625152,
      "fees30dUsd": 9969069,
      "feeToVolume30dPct": 0.05598516796362334,
      "weightedChange7dPct": -11.545752809063233,
      "strongMarkets": 1,
      "watchMarkets": 1,
      "atRiskMarkets": 0,
      "score": 69,
      "confidence": 75,
      "status": "Monitor",
      "sourceUrls": [
        "https://defillama.com/protocol/aerodrome-slipstream",
        "https://defillama.com/protocol/aerodrome-v1"
      ],
      "updatedAt": "2026-06-19T03:26:58.701Z"
    },
    {
      "id": "pancakeswap",
      "name": "PancakeSwap",
      "segment": "Cross-chain DEX",
      "networks": [
        "Base"
      ],
      "marketCount": 1,
      "volume30dUsd": 3926905794,
      "fees30dUsd": 590476,
      "feeToVolume30dPct": 0.015036673426243135,
      "weightedChange7dPct": -7.69,
      "strongMarkets": 1,
      "watchMarkets": 0,
      "atRiskMarkets": 0,
      "score": 67,
      "confidence": 55,
      "status": "Monitor",
      "sourceUrls": [
        "https://defillama.com/protocol/pancakeswap-amm-v3"
      ],
      "updatedAt": "2026-06-19T03:26:58.701Z"
    },
    {
      "id": "sushiswap",
      "name": "SushiSwap",
      "segment": "Cross-chain DEX",
      "networks": [
        "OP Mainnet"
      ],
      "marketCount": 1,
      "volume30dUsd": 1084345,
      "fees30dUsd": 468,
      "feeToVolume30dPct": 0.04315969548437075,
      "weightedChange7dPct": 14.05,
      "strongMarkets": 0,
      "watchMarkets": 1,
      "atRiskMarkets": 0,
      "score": 56,
      "confidence": 55,
      "status": "Monitor",
      "sourceUrls": [
        "https://defillama.com/protocol/sushiswap-v3"
      ],
      "updatedAt": "2026-06-19T03:26:58.701Z"
    },
    {
      "id": "curve",
      "name": "Curve",
      "segment": "Stable liquidity venue",
      "networks": [
        "OP Mainnet",
        "Unichain"
      ],
      "marketCount": 2,
      "volume30dUsd": 4222769,
      "fees30dUsd": 1603,
      "feeToVolume30dPct": 0.03796087354056071,
      "weightedChange7dPct": -21.85,
      "strongMarkets": 0,
      "watchMarkets": 1,
      "atRiskMarkets": 1,
      "score": 55,
      "confidence": 67,
      "status": "Monitor",
      "sourceUrls": [
        "https://defillama.com/protocol/curve-dex"
      ],
      "updatedAt": "2026-06-19T03:26:58.701Z"
    },
    {
      "id": "balancer",
      "name": "Balancer",
      "segment": "Managed liquidity venue",
      "networks": [
        "OP Mainnet"
      ],
      "marketCount": 1,
      "volume30dUsd": 762077,
      "fees30dUsd": 261,
      "feeToVolume30dPct": 0.03424850769672881,
      "weightedChange7dPct": 1400,
      "strongMarkets": 0,
      "watchMarkets": 1,
      "atRiskMarkets": 0,
      "score": 54,
      "confidence": 55,
      "status": "Monitor",
      "sourceUrls": [
        "https://defillama.com/protocol/balancer-v2"
      ],
      "updatedAt": "2026-06-19T03:26:58.701Z"
    },
    {
      "id": "kim-exchange",
      "name": "KIM Exchange",
      "segment": "Mode-native DEX",
      "networks": [
        "Mode"
      ],
      "marketCount": 2,
      "volume30dUsd": 137185,
      "fees30dUsd": 109,
      "feeToVolume30dPct": 0.07945475088384299,
      "weightedChange7dPct": 57.089298392681414,
      "strongMarkets": 0,
      "watchMarkets": 1,
      "atRiskMarkets": 1,
      "score": 49,
      "confidence": 75,
      "status": "Monitor",
      "sourceUrls": [
        "https://defillama.com/protocol/kim-exchange-v3",
        "https://defillama.com/protocol/kim-exchange-v2"
      ],
      "updatedAt": "2026-06-19T03:26:58.701Z"
    }
  ],
  "metrics": {
    "totalVolume30dUsd": 34875209808,
    "totalFees30dUsd": 35192032,
    "readyProtocols": 2,
    "watchMarkets": 19
  }
}
